turkle_review/__init__.py
turkle_review/admin.py
turkle_review/apps.py
turkle_review/views.py
turkle_review/templates/turkle_review/review.html
turkle_review-0.2.dist-info/LICENSE
turkle_review-0.2.dist-info/METADATA
turkle_review-0.2.dist-info/WHEEL
turkle_review-0.2.dist-info/top_level.txt
turkle_review-0.2.dist-info/RECORD
