Metadata-Version: 2.1
Name: turkle-review
Version: 0.2
Summary: Adds batch review capability to Turkle
Home-page: https://github.com/hltcoe/turkle-review
Classifier: Framework :: Django
Classifier: Programming Language :: Python :: 3
Classifier: License :: OSI Approved :: MIT License
Classifier: Operating System :: OS Independent
Requires-Python: >=3.8
License-File: LICENSE
Requires-Dist: Django >=4.2
